tcgdex_sdk-2.2.0.dist-info/METADATA
tcgdex_sdk-2.2.0.dist-info/WHEEL
tcgdex_sdk-2.2.0.dist-info/entry_points.txt
tcgdexsdk/__init__.py
tcgdexsdk/endpoints/Endpoint.py
tcgdexsdk/enums.py
tcgdexsdk/models/Card.py
tcgdexsdk/models/CardResume.py
tcgdexsdk/models/IntEndpoint.py
tcgdexsdk/models/Model.py
tcgdexsdk/models/Model.pyi
tcgdexsdk/models/Serie.py
tcgdexsdk/models/SerieResume.py
tcgdexsdk/models/Set.py
tcgdexsdk/models/SetResume.py
tcgdexsdk/models/StringEndpoint.py
tcgdexsdk/models/__init__.py
tcgdexsdk/models/subs.py
tcgdexsdk/query.py
tcgdexsdk/tcgdex.py
tcgdexsdk/utils.py
tcgdex_sdk-2.2.0.dist-info/RECORD
