Metadata-Version: 2.1
Name: tcgdex-sdk
Version: 2.2.0
Summary: A fast, type-safe Python SDK for the TCGdex API. Query Pokémon Trading Card Game data easily. 🚀
Keywords: api,pokemon,tcg,sdk,trading,card,pokemon-api,pokemon-cards,tcgdex
Author: HellLord77
Author-Email: Avior <git@avior.me>
Maintainer-Email: Avior <git@avior.me>
License: MIT
Classifier: Development Status :: 5 - Production/Stable
Classifier: Intended Audience :: Developers
Classifier: Operating System :: OS Independent
Classifier: License :: OSI Approved :: MIT License
Classifier: Programming Language :: Python :: 3
Classifier: Programming Language :: Python :: 3.8
Classifier: Programming Language :: Python :: 3.9
Classifier: Programming Language :: Python :: 3.10
Classifier: Programming Language :: Python :: 3.11
Classifier: Programming Language :: Python :: 3.12
Classifier: Programming Language :: Python :: 3 :: Only
Classifier: Topic :: Software Development :: Libraries :: Python Modules
Project-URL: homepage, https://tcgdex.dev/sdks/python
Project-URL: source, https://github.com/tcgdex/python-sdk
Project-URL: download, https://github.com/tcgdex/python-sdk/releases/latest
Project-URL: changelog, https://github.com/tcgdex/python-sdk/releases/latest
Project-URL: releasenotes, https://github.com/tcgdex/python-sdk/releases/latest
Project-URL: documentation, https://tcgdex.dev/sdks/python
Project-URL: issues, https://github.com/tcgdex/python-sdk/issues
Project-URL: funding, https://github.com/sponsors/tcgdex
Requires-Python: >=3.8
Requires-Dist: dacite<2.0.0,>=1.8.1
